hello_world_verysimplemodule/__init__.py
hello_world_verysimplemodule/add.py
hello_world_verysimplemodule/subtract.py
hello_world_verysimplemodule/extras/__init__.py
hello_world_verysimplemodule/extras/divide.py
hello_world_verysimplemodule/extras/multiply.py
hello_world_verysimplemodule-0.0.1.dist-info/METADATA
hello_world_verysimplemodule-0.0.1.dist-info/WHEEL
hello_world_verysimplemodule-0.0.1.dist-info/top_level.txt
hello_world_verysimplemodule-0.0.1.dist-info/RECORD
